bwloguru/LogUtil.py
bwloguru/__init__.py
bwloguru-0.1.dist-info/METADATA
bwloguru-0.1.dist-info/WHEEL
bwloguru-0.1.dist-info/top_level.txt
bwloguru-0.1.dist-info/RECORD
