Metadata-Version: 2.1
Name: bwloguru
Version: 0.1
Summary: 一个基于loguru封装的日志记录器
Author-email: bw <1329696875@qq.com>
Classifier: Programming Language :: Python :: 3
Classifier: License :: OSI Approved :: MIT License
Classifier: Operating System :: OS Independent
Requires-Python: >=3.7
Requires-Dist: loguru >=0.7.2
